pyreqpp/__init__.py
pyreqpp/__main__.py
pyreqpp/cli.py
pyreqpp/utils/__init__.py
pyreqpp/utils/run.py
pyreqpp-0.1.0.dist-info/WHEEL
pyreqpp-0.1.0.dist-info/METADATA
pyreqpp-0.1.0.dist-info/RECORD
